GenBankToLib/__init__.py
GenBankToLib/bacteria.py
GenBankToLib/genbank.py
GenBankToLib/genbank_to_json.py
GenBankToLib/main.py
GenBankToLib/version.py
genbank_to-0.54.dist-info/licenses/LICENSE
genbank_to-0.54.dist-info/METADATA
genbank_to-0.54.dist-info/WHEEL
genbank_to-0.54.dist-info/entry_points.txt
genbank_to-0.54.dist-info/top_level.txt
genbank_to-0.54.dist-info/RECORD
