Metadata-Version: 2.4
Name: genbank_to
Version: 0.54
Summary: Convert GenBank format files to a swath of other formats
Author-email: Rob Edwards <raedwards@gmail.com>
License: MIT License
Project-URL: Homepage, https://github.com/linsalrob/genbank_to
Project-URL: Repository, https://github.com/linsalrob/genbank_to
Project-URL: Issues, https://github.com/linsalrob/genbank_to/issues
Keywords: genbank,bioinformatics,microbiology,genome,genomics
Classifier: Development Status :: 4 - Beta
Classifier: Intended Audience :: Science/Research
Classifier: Natural Language :: English
Classifier: Operating System :: MacOS :: MacOS X
Classifier: Operating System :: POSIX :: Linux
Classifier: Operating System :: Unix
Classifier: Programming Language :: Python :: 3
Classifier: Programming Language :: Python :: 3.9
Classifier: Programming Language :: Python :: 3.10
Classifier: Programming Language :: Python :: 3.11
Classifier: Programming Language :: Python :: 3.12
Classifier: Topic :: Scientific/Engineering :: Bio-Informatics
Requires-Python: >=3.9
License-File: LICENSE
Requires-Dist: biopython>=1.74
Requires-Dist: numpy>=1.16.0
Requires-Dist: pandas
Requires-Dist: bcbio-gff>=0.6.6
Provides-Extra: test
Requires-Dist: pytest>=7.0; extra == "test"
Dynamic: license-file
